github_data_extractor/__init__.py
github_data_extractor/src/__init__.py
github_data_extractor/src/unified_extractor.py
github_data_extractor-0.0.11.dist-info/METADATA
github_data_extractor-0.0.11.dist-info/WHEEL
github_data_extractor-0.0.11.dist-info/top_level.txt
github_data_extractor-0.0.11.dist-info/RECORD
