Metadata-Version: 2.2
Name: github_data_extractor
Version: 0.0.11
Summary: A package to extract GitHub repository insights
Home-page: https://github.com/aadityayadav/github_data_extractor
Author: Aaditya Yadav/ Vibhak Golchha
Author-email: aadityayadav2003@gmail.com, vibhakgolchha@gmail.com
License: MIT
Classifier: License :: OSI Approved :: MIT License
Classifier: Programming Language :: Python :: 3.5
Classifier: Operating System :: OS Independent
Requires-Python: >=3.5
Requires-Dist: pydriller>=1.9
Requires-Dist: PyGithub>=1.54
Requires-Dist: requests>=2.20.0
Provides-Extra: dev
Requires-Dist: pytest>=7.0; extra == "dev"
Requires-Dist: twine>=4.0.2; extra == "dev"
Requires-Dist: python-dotenv>=1.0.0; extra == "dev"
Requires-Dist: wheel>=0.37.0; extra == "dev"
Dynamic: author
Dynamic: author-email
Dynamic: classifier
Dynamic: description
Dynamic: description-content-type
Dynamic: home-page
Dynamic: license
Dynamic: provides-extra
Dynamic: requires-dist
Dynamic: requires-python
Dynamic: summary
